iSpark-1.0.4.dist-info/METADATA
iSpark-1.0.4.dist-info/RECORD
iSpark-1.0.4.dist-info/WHEEL
iSpark-1.0.4.dist-info/top_level.txt
ispark/SparkStarter.py
ispark/__init__.py
